test_aiohttp/__init__.py
test_aiohttp/rsps.py
test_aiohttp/testcases.py
testing_aiohttp-0.0.7.dist-info/DESCRIPTION.rst
testing_aiohttp-0.0.7.dist-info/LICENSE.txt
testing_aiohttp-0.0.7.dist-info/METADATA
testing_aiohttp-0.0.7.dist-info/RECORD
testing_aiohttp-0.0.7.dist-info/WHEEL
testing_aiohttp-0.0.7.dist-info/metadata.json
testing_aiohttp-0.0.7.dist-info/top_level.txt
tests/__init__.py
tests/test_rsps.py
