Metadata-Version: 2.0
Name: testing-aiohttp
Version: 0.0.7
Summary: UNKNOWN
Home-page: https://github.com/genericclient/testing-aiohttp
Author: Flavio Curella
Author-email: flavio.curella@gmail.com
License: UNKNOWN
Platform: UNKNOWN
Classifier: Development Status :: 4 - Beta
Classifier: Environment :: Web Environment
Classifier: Intended Audience :: Developers
Classifier: Operating System :: OS Independent
Classifier: Programming Language :: Python :: 3
Classifier: License :: OSI Approved :: MIT License
Requires-Dist: aiohttp (<2.4,>=2.3.2)
